dftools/__init__.py
dftools/draw.py
dftools/fitting.py
dftools/numpy.py
dftools/smooth.py
dftools/stats.py
dftools/transform.py
dftools-0.2.6.dist-info/LICENSE
dftools-0.2.6.dist-info/METADATA
dftools-0.2.6.dist-info/WHEEL
dftools-0.2.6.dist-info/top_level.txt
dftools-0.2.6.dist-info/RECORD
