Metadata-Version: 2.1
Name: dftools
Version: 0.2.6
Summary: dataframe tools
Home-page: UNKNOWN
Author: Shane Breeze
Author-email: sdb15@ic.ac.uk
License: UNKNOWN
Platform: UNKNOWN
Classifier: Programming Language :: Python :: 3
Classifier: License :: OSI Approved :: MIT License
Classifier: Operating System :: OS Independent
Classifier: Topic :: Software Development :: Libraries :: Python Modules
Classifier: Topic :: Utilities
Classifier: Development Status :: 3 - Alpha
Requires-Dist: numpy (>=1.18.1)
Requires-Dist: pandas (>=1.0.1)
Requires-Dist: matplotlib (>=3.1.2)
Requires-Dist: scipy (>=1.4.1)
Requires-Dist: numdifftools (>=0.9.39)
Requires-Dist: iminuit (>=1.3.8)
